odoo/addons/sale_invoice_delivery_state/README.rst
odoo/addons/sale_invoice_delivery_state/__init__.py
odoo/addons/sale_invoice_delivery_state/__manifest__.py
odoo/addons/sale_invoice_delivery_state/i18n/fr.po
odoo/addons/sale_invoice_delivery_state/i18n/sale_invoice_delivery_state.pot
odoo/addons/sale_invoice_delivery_state/models/__init__.py
odoo/addons/sale_invoice_delivery_state/models/partner.py
odoo/addons/sale_invoice_delivery_state/models/sale.py
odoo/addons/sale_invoice_delivery_state/readme/CONTRIBUTORS.rst
odoo/addons/sale_invoice_delivery_state/readme/DESCRIPTION.rst
odoo/addons/sale_invoice_delivery_state/static/description/icon.png
odoo/addons/sale_invoice_delivery_state/static/description/index.html
odoo/addons/sale_invoice_delivery_state/tests/__init__.py
odoo/addons/sale_invoice_delivery_state/tests/test_sale_invoice_delivery_state.py
odoo/addons/sale_invoice_delivery_state/views/partner.xml
odoo14_addon_sale_invoice_delivery_state-14.0.1.0.1.dist-info/METADATA
odoo14_addon_sale_invoice_delivery_state-14.0.1.0.1.dist-info/WHEEL
odoo14_addon_sale_invoice_delivery_state-14.0.1.0.1.dist-info/top_level.txt
odoo14_addon_sale_invoice_delivery_state-14.0.1.0.1.dist-info/RECORD
